CHANGES.txt
LICENSE.txt
MANIFEST.in
README.txt
setup.py
js/__init__.py
js.jquery_jstorage.egg-info/PKG-INFO
js.jquery_jstorage.egg-info/SOURCES.txt
js.jquery_jstorage.egg-info/dependency_links.txt
js.jquery_jstorage.egg-info/entry_points.txt
js.jquery_jstorage.egg-info/namespace_packages.txt
js.jquery_jstorage.egg-info/not-zip-safe
js.jquery_jstorage.egg-info/requires.txt
js.jquery_jstorage.egg-info/top_level.txt
js/jquery_jstorage/__init__.py
js/jquery_jstorage/test_jstorage.txt
js/jquery_jstorage/resources/jstorage.js
js/jquery_jstorage/resources/jstorage.min.js