Metadata-Version: 1.0
Name: js.jquery-jstorage
Version: 0.3.2-1
Summary: Fanstatic packaging of jStorage
Home-page: UNKNOWN
Author: Fanstatic Developers
Author-email: fanstatic@googlegroups.com
License: BSD
Platform: UNKNOWN
